[
  {
    "py/object": "model.group.Group",
    "name": "",
    "header": "",
    "footer": "",
    "id": null
  },
  {
    "py/object": "model.group.Group",
    "name": "nameKH3eV ",
    "header": "headerv",
    "footer": "footerXA",
    "id": null
  },
  {
    "py/object": "model.group.Group",
    "name": "nameK 6s",
    "header": "header ",
    "footer": "footerVRvYw 35SC ",
    "id": null
  },
  {
    "py/object": "model.group.Group",
    "name": "name7kU 6RZf",
    "header": "headerd4lvSlod Lu  HMlMJE",
    "footer": "footerN 889  5G",
    "id": null
  },
  {
    "py/object": "model.group.Group",
    "name": "nameWBU6L utN",
    "header": "headerq",
    "footer": "footer JAux6JXFgRNfM",
    "id": null
  },
  {
    "py/object": "model.group.Group",
    "name": "nameW3 FC 8U",
    "header": "header ",
    "footer": "footeriJeX RnTIfw bEW",
    "id": null
  }
]